pytest_power/__init__.py
pytest_power/pytest_power.py
pytest_power/utils.py
pytest_power-1.0.1.dist-info/entry_points.txt
pytest_power-1.0.1.dist-info/LICENSE
pytest_power-1.0.1.dist-info/WHEEL
pytest_power-1.0.1.dist-info/METADATA
pytest_power-1.0.1.dist-info/RECORD
